_py3coap.cp38-win32.h
_py3coap.cp38-win32.pyd
py3coap/__init__.py
py3coap/errors.py
py3coap/py3coap.py
py3coap-0.9.4.data/data/src/py3coap/go.mod
py3coap-0.9.4.data/data/src/py3coap/py3coap.c
py3coap-0.9.4.data/data/src/py3coap/py3coap.h
py3coap-0.9.4.data/scripts/pycoap-client
py3coap-0.9.4.dist-info/METADATA
py3coap-0.9.4.dist-info/WHEEL
py3coap-0.9.4.dist-info/top_level.txt
py3coap-0.9.4.dist-info/RECORD
