Metadata-Version: 2.1
Name: py3coap
Version: 0.9.4
Summary: A GOLANG python extension for COAP/COAPS-requests
Home-page: https://github.com/moroen/pycoap
Author: moroen
Author-email: no@email.com
License: UNKNOWN
Platform: UNKNOWN
Classifier: License :: OSI Approved :: MIT License
Classifier: Programming Language :: Python :: 3.6
Classifier: Programming Language :: Python :: Implementation :: CPython
